src/__init__.py
src/cli.py
src/config.py
src/console.py
src/fetch.py
src/history.py
status_fetch-1.0.1.dist-info/METADATA
status_fetch-1.0.1.dist-info/WHEEL
status_fetch-1.0.1.dist-info/entry_points.txt
status_fetch-1.0.1.dist-info/top_level.txt
status_fetch-1.0.1.dist-info/RECORD
