Metadata-Version: 2.1
Name: status-fetch
Version: 1.0.1
Summary: Fetch the status of your website
Home-page: https://github.com/status-hub/fetch/
Author: Status
License: GNU
Keywords: status,status CLI,status-fetch,fetch
Platform: UNKNOWN
Requires-Dist: click
Requires-Dist: progress
Requires-Dist: pyyaml
Requires-Dist: requests
Requires-Dist: termcolor
Requires-Dist: xmltodict
